gammaj/__init__.py
gammaj/__main__.py
gammaj/parser.py
gammaj/run.py
gammaj/utilsbox.py
GammaJ-6.dist-info/LICENSE
GammaJ-6.dist-info/METADATA
GammaJ-6.dist-info/WHEEL
GammaJ-6.dist-info/entry_points.txt
GammaJ-6.dist-info/top_level.txt
GammaJ-6.dist-info/RECORD
