Metadata-Version: 2.1
Name: GammaJ
Version: 6
Summary: A small lightweight language that combines Python and HTML.
Home-page: https://github.com/elemenom/gammaj
Author: elemenom
Author-email: pixilreal@gmail.com
Classifier: Programming Language :: Python :: 3
Classifier: License :: OSI Approved :: GNU General Public License v3 (GPLv3)
Classifier: Operating System :: OS Independent
Requires-Python: >=3.12
License-File: LICENSE
